xtensor_pp/__init__.py
xtensor_pp/xtensor_pp.py
xtensor_pp-0.0.2.dist-info/METADATA
xtensor_pp-0.0.2.dist-info/WHEEL
xtensor_pp-0.0.2.dist-info/licenses/LICENSE
xtensor_pp-0.0.2.dist-info/RECORD
