Metadata-Version: 2.3
Name: xtensor_pp
Version: 0.0.2
Summary: A gdb pretty printer for xtensor 
Project-URL: Homepage, https://github.com/pypa/sampleproject
Project-URL: Issues, https://github.com/pypa/sampleproject/issues
Author-email: Eugène Sanscartier <eugene.sanscartier@gmail.com>
License-File: LICENSE
Classifier: License :: OSI Approved :: MIT License
Classifier: Operating System :: OS Independent
Classifier: Programming Language :: Python :: 3
Requires-Python: >=3.8
